hoodat_utils/__init__.py
hoodat_utils/alembic/README
hoodat_utils/alembic/env.py
hoodat_utils/alembic/script.py.mako
hoodat_utils/alembic/versions/02d94cd8a1ce_changed_pca_object_features_id_colname_.py
hoodat_utils/alembic/versions/04074343ab1f_session_info_timestamp_as_integer.py
hoodat_utils/alembic/versions/08a49ff86510_misspelt_timestamp_add_process.py
hoodat_utils/alembic/versions/0c2d591e286e_add_another_decimal_place_to_detector_.py
hoodat_utils/alembic/versions/11bf77399e0f_linked_videos_with_series.py
hoodat_utils/alembic/versions/1263b617af57_removed_character_labels_relationship_.py
hoodat_utils/alembic/versions/1b019da65d4f_add_columns_to_actors.py
hoodat_utils/alembic/versions/27c3ed745239_character_labels_needs_a_key_col.py
hoodat_utils/alembic/versions/2a3a19b776c5_added_process_order_to_processes_table.py
hoodat_utils/alembic/versions/335e48271836_changed_videos_upload_timestamp_to_.py
hoodat_utils/alembic/versions/3382cd293e50_changes.py
hoodat_utils/alembic/versions/499e890aa148_added_processes_and_triggers_tables.py
hoodat_utils/alembic/versions/4fdaad670a35_add_object_pca_features_table.py
hoodat_utils/alembic/versions/522cd0c45168_added_uniqueness_to_youtube_link_column.py
hoodat_utils/alembic/versions/52cd9c67142d_unique_constraint_in_seasons.py
hoodat_utils/alembic/versions/554178515c27_added_not_nullable_to_user_id.py
hoodat_utils/alembic/versions/55b537e0c4db_added_youtube_link_column.py
hoodat_utils/alembic/versions/60a827c82297_added_seasons_table.py
hoodat_utils/alembic/versions/63fcb6f73f50_test_revision.py
hoodat_utils/alembic/versions/6906302f0e6e_some_uniqueness_constraints.py
hoodat_utils/alembic/versions/6b385de534b7_added_dlib_face_tables_2.py
hoodat_utils/alembic/versions/6c12ddacf663_relationship_between_episodes_and_videos.py
hoodat_utils/alembic/versions/6c21c8bf0003_change_numeric_decimals_of_detector_.py
hoodat_utils/alembic/versions/7352cf06437d_linked_videos_and_actor_groups.py
hoodat_utils-0.2.0.dist-info/WHEEL
hoodat_utils-0.2.0.dist-info/LICENSE.txt
hoodat_utils-0.2.0.dist-info/METADATA
hoodat_utils-0.2.0.dist-info/RECORD
