Metadata-Version: 2.1
Name: hoodat-utils
Version: 0.2.0
Summary: 
Author: Eugene Brown
Author-email: efbbrown@gmail.com
Requires-Python: >=3.8,<4.0
Classifier: Programming Language :: Python :: 3
Classifier: Programming Language :: Python :: 3.8
Classifier: Programming Language :: Python :: 3.9
Classifier: Programming Language :: Python :: 3.10
Classifier: Programming Language :: Python :: 3.11
Requires-Dist: Flask-Login (>=0.6.0,<0.7.0)
Requires-Dist: Flask-SQLAlchemy (>=2.5.1,<3.0.0)
Requires-Dist: PyMySQL (>=1.0.2,<2.0.0)
Requires-Dist: SQLAlchemy (>=1.4.35,<2.0.0)
Requires-Dist: alembic (>=1.8.1,<2.0.0)
Requires-Dist: google-cloud-storage (>=1.20.0,<2.0.0)
Requires-Dist: pandas (>=1.4.2,<2.0.0)
Requires-Dist: pytest (>=7.1.1,<8.0.0)
